xscrapers/__init__.py
xscrapers/_base.py
xscrapers/tools/__init__.py
xscrapers/tools/parser.py
xscrapers/wait.py
xscrapers/webdriver.py
xscrapers/webscraper.py
xscrapers-0.0.7.dist-info/LICENSE
xscrapers-0.0.7.dist-info/WHEEL
xscrapers-0.0.7.dist-info/METADATA
xscrapers-0.0.7.dist-info/RECORD
