Metadata-Version: 2.1
Name: xscrapers
Version: 0.0.7
Summary: A simple webscraper library
Home-page: https://github.com/juliandwain/xscrapers
License: MIT
Author: Julian Stang
Author-email: julian.stang@tum.de
Requires-Python: >=3.8,<4.0
Classifier: License :: OSI Approved :: MIT License
Classifier: Programming Language :: Python :: 3
Classifier: Programming Language :: Python :: 3.8
Classifier: Programming Language :: Python :: 3.9
Requires-Dist: beautifulsoup4 (>=4.9.3,<5.0.0)
Requires-Dist: fake-useragent (>=0.1.11,<0.2.0)
Requires-Dist: html5lib (>=1.1,<2.0)
Requires-Dist: numpy (>=1.20.2,<2.0.0)
Requires-Dist: pandas (>=1.2.3,<2.0.0)
Requires-Dist: requests (>=2.25.1,<3.0.0)
Requires-Dist: selenium (>=3.141.0,<4.0.0)
Project-URL: Repository, https://github.com/juliandwain/xscrapers
